whatthelang
