Metadata-Version: 1.1
Name: whatthelang
Version: 1.0.1
Summary: Lightning Fast Language Prediction powered by FastText.
Home-page: https://github.com/indix/whatthelang
Author: Krishna Sangeeth
Author-email: kskrishnasangeeth@gmail.com
License:                                  Apache License
